myCalculatorPackage_jw/__init__.py
myCalculatorPackage_jw/division/__init__.py
myCalculatorPackage_jw/division/divide.py
myCalculatorPackage_jw/multiplication/__init__.py
myCalculatorPackage_jw/multiplication/multiply.py
myCalculatorPackage_jw-0.0.2.dist-info/LICENSE.txt
myCalculatorPackage_jw-0.0.2.dist-info/METADATA
myCalculatorPackage_jw-0.0.2.dist-info/WHEEL
myCalculatorPackage_jw-0.0.2.dist-info/top_level.txt
myCalculatorPackage_jw-0.0.2.dist-info/RECORD
